setup.py
tvtags.py
tvdb_api/__init__.py
tvdb_api/cache.py
tvdb_api/tvdb_api.py
tvdb_api/tvdb_exceptions.py
tvdb_api/tvdb_ui.py
tvtags.egg-info/PKG-INFO
tvtags.egg-info/SOURCES.txt
tvtags.egg-info/dependency_links.txt
tvtags.egg-info/entry_points.txt
tvtags.egg-info/requires.txt
tvtags.egg-info/top_level.txt