Metadata-Version: 1.0
Name: tvtags
Version: 0.7.0
Summary: Automagicly media tagger.
Home-page: http://github.com/tuxtof/tvtags
Author: tuxtof
Author-email: dev@geo6.net
License: GPLv2
Platform: UNKNOWN
